[
  {
    "title": "뼈아픈 건설 부진…KDI “올해 韓 성장률 0%대”",
    "link": "https://www.mk.co.kr/news/business/11392541",
    "pub_date": "Wed, 13 Aug 2025 10:59:29 +09:00",
    "fetched_at": "2025-08-13T02:11:33.048400Z"
  },
  {
    "title": "특별사면 후폭풍…보수 야당∙보수 전직 대통령 국민임명식 불참",
    "link": "https://www.mk.co.kr/news/business/11392533",
    "pub_date": "Wed, 13 Aug 2025 10:54:12 +09:00",
    "fetched_at": "2025-08-13T02:11:33.048410Z"
  },
  {
    "title": "[뉴욕증시] 9월 금리인하 기대감에…S&P·나스닥 사상 최고치",
    "link": "https://www.mk.co.kr/news/world/11392389",
    "pub_date": "Wed, 13 Aug 2025 08:53:23 +09:00",
    "fetched_at": "2025-08-13T02:11:33.048415Z"
  },
  {
    "title": "노란봉투법, 경영 vs 노동…핵심 쟁점 3가지 [스페셜리포트]",
    "link": "https://www.mk.co.kr/news/economy/11390313",
    "pub_date": "Wed, 13 Aug 2025 07:13:00 +09:00",
    "fetched_at": "2025-08-13T02:11:33.048419Z"
  },
  {
    "title": "노란봉투법 부작용 줄이려면? [스페셜리포트]",
    "link": "https://www.mk.co.kr/news/economy/11390315",
    "pub_date": "Wed, 13 Aug 2025 07:13:00 +09:00",
    "fetched_at": "2025-08-13T02:11:33.048423Z"
  }
]