[
  {
    "title": "명인제약 창업주 이행명 회장, 경영 일선 물러난다",
    "link": "https://www.hankyung.com/article/202602030528i",
    "pub_date": "Tue, 03 Feb 2026 11:30:37 +0900",
    "fetched_at": "2026-02-03T03:12:04.472500Z"
  },
  {
    "title": "원텍, '라비앙' 멕시코 허가…브라질 이어 중남미 '양날개' 완성",
    "link": "https://www.hankyung.com/article/202602030434i",
    "pub_date": "Tue, 03 Feb 2026 10:51:59 +0900",
    "fetched_at": "2026-02-03T03:12:04.472511Z"
  },
  {
    "title": "\"위고비 맞고 카카오로 건강관리\"…카카오헬스케어 '비만환자 지원 서비스' 도입",
    "link": "https://www.hankyung.com/article/202602030370i",
    "pub_date": "Tue, 03 Feb 2026 10:39:35 +0900",
    "fetched_at": "2026-02-03T03:12:04.472516Z"
  },
  {
    "title": "뉴로핏, '뉴로핏 아쿠아 AD 플러스' FDA 510(k) 획득… 세 번째 美 인허가",
    "link": "https://www.hankyung.com/article/202602030254i",
    "pub_date": "Tue, 03 Feb 2026 10:23:49 +0900",
    "fetched_at": "2026-02-03T03:12:04.472521Z"
  },
  {
    "title": "반도체 수율 가르는 플라즈마 신호, AI로 즉시 판독할 수 있는 기술 나왔다",
    "link": "https://www.hankyung.com/article/202602030237i",
    "pub_date": "Tue, 03 Feb 2026 10:05:44 +0900",
    "fetched_at": "2026-02-03T03:12:04.472525Z"
  }
]