[
  {
    "title": "[속보] 투표용지 합수본, 선관위 관계자 12명 압수수색",
    "link": "https://www.mk.co.kr/news/business/12081761",
    "pub_date": "Wed, 24 Jun 2026 11:17:43 +09:00",
    "fetched_at": "2026-06-24T04:17:09.837421Z"
  },
  {
    "title": "韓 증시, MSCI 선진국지수 편입 또 불발…내년 재도전",
    "link": "https://www.mk.co.kr/news/business/12081707",
    "pub_date": "Wed, 24 Jun 2026 10:52:56 +09:00",
    "fetched_at": "2026-06-24T04:17:09.837432Z"
  },
  {
    "title": "“꼬리가 몸통 흔든다”…증시 흔드는 레버리지 ETF의 그늘",
    "link": "https://www.mk.co.kr/news/economy/12081704",
    "pub_date": "Wed, 24 Jun 2026 10:50:50 +09:00",
    "fetched_at": "2026-06-24T04:17:09.837438Z"
  },
  {
    "title": "[속보] 코스피 4% 급등에 8500선 회복…삼성전자 10%↑",
    "link": "https://www.mk.co.kr/news/economy/12081581",
    "pub_date": "Wed, 24 Jun 2026 09:36:00 +09:00",
    "fetched_at": "2026-06-24T04:17:09.837442Z"
  },
  {
    "title": "반도체주 매도세에 동반 하락…나스닥 2.2%↓[뉴욕증시]",
    "link": "https://www.mk.co.kr/news/world/12081561",
    "pub_date": "Wed, 24 Jun 2026 09:00:33 +09:00",
    "fetched_at": "2026-06-24T04:17:09.837445Z"
  }
]