[
  {
    "title": "“‘사스포칼립스’ 이제 안녕?”…소프트웨어 관련株 반등",
    "link": "https://www.mk.co.kr/news/business/12061258",
    "pub_date": "Sat, 30 May 2026 13:00:00 +09:00",
    "fetched_at": "2026-05-30T04:09:44.084475Z"
  },
  {
    "title": "‘인생카드’ 추천해준다는데...소비 패턴 기반 추천 서비스 뭐길래?",
    "link": "https://www.mk.co.kr/news/economy/12061156",
    "pub_date": "Sat, 30 May 2026 13:00:00 +09:00",
    "fetched_at": "2026-05-30T04:09:44.084486Z"
  },
  {
    "title": "[속보] 美국방 “부유한 동맹국 방위비 대신 내주던 시대 끝났다”",
    "link": "https://www.mk.co.kr/news/business/12061844",
    "pub_date": "Sat, 30 May 2026 10:37:47 +09:00",
    "fetched_at": "2026-05-30T04:09:44.084492Z"
  },
  {
    "title": "지금 사둬야 한다는데...여의도가 콕 집은 유망 종목은",
    "link": "https://www.mk.co.kr/news/economy/12061150",
    "pub_date": "Sat, 30 May 2026 09:00:00 +09:00",
    "fetched_at": "2026-05-30T04:09:44.084496Z"
  },
  {
    "title": "이재용 회장도 사전투표…한남동 주민센터서 포착",
    "link": "https://www.mk.co.kr/news/business/12061369",
    "pub_date": "Fri, 29 May 2026 16:57:34 +09:00",
    "fetched_at": "2026-05-30T04:09:44.084499Z"
  }
]