[
  {
    "title": "베이커리카페 절반이 상속 꼼수?…가업상속공제 확 바뀐다",
    "link": "https://www.mk.co.kr/news/business/12009962",
    "pub_date": "Tue, 07 Apr 2026 11:16:38 +09:00",
    "fetched_at": "2026-04-07T03:23:11.431985Z"
  },
  {
    "title": "[속보] 강훈식 “원유·나프타 확보 위해 사우디·오만·카자흐 방문”",
    "link": "https://www.mk.co.kr/news/world/12009936",
    "pub_date": "Tue, 07 Apr 2026 10:56:31 +09:00",
    "fetched_at": "2026-04-07T03:23:11.431997Z"
  },
  {
    "title": "안소영 개인전 <마음에 잔잔히 머무는 풍경>",
    "link": "https://www.mk.co.kr/news/business/12009852",
    "pub_date": "Tue, 07 Apr 2026 09:50:57 +09:00",
    "fetched_at": "2026-04-07T03:23:11.432002Z"
  },
  {
    "title": "[속보] 서울 휘발유 2000원 돌파…경유도 1980원 눈앞",
    "link": "https://www.mk.co.kr/news/business/12009848",
    "pub_date": "Tue, 07 Apr 2026 09:45:51 +09:00",
    "fetched_at": "2026-04-07T03:23:11.432007Z"
  },
  {
    "title": "미·이란 협상 낙관론…3대 지수 상승 마감 [뉴욕 증시]",
    "link": "https://www.mk.co.kr/news/world/12009763",
    "pub_date": "Tue, 07 Apr 2026 09:03:25 +09:00",
    "fetched_at": "2026-04-07T03:23:11.432011Z"
  }
]