[
  {
    "title": "“호텔신라 10만원 간다고?”...中 관광객 늘자 주가 ‘쑥’ [오늘, 이 종목]",
    "link": "https://www.mk.co.kr/news/economy/12028227",
    "pub_date": "Mon, 27 Apr 2026 12:47:51 +09:00",
    "fetched_at": "2026-04-27T03:52:57.759880Z"
  },
  {
    "title": "우주로 향하는 서학개미…증권가는 ‘이것’ 조심하라는데",
    "link": "https://www.mk.co.kr/news/economy/12028226",
    "pub_date": "Mon, 27 Apr 2026 12:41:28 +09:00",
    "fetched_at": "2026-04-27T03:52:57.759890Z"
  },
  {
    "title": "“도저히 못 버티겠어요”…경매 신청 13년 만에 최대치",
    "link": "https://www.mk.co.kr/news/economy/12028225",
    "pub_date": "Mon, 27 Apr 2026 12:37:17 +09:00",
    "fetched_at": "2026-04-27T03:52:57.759895Z"
  },
  {
    "title": "[속보] 선거유세 중 ‘음료테러’… 개혁신당 정이한 부산시장 후보 응급실 이송",
    "link": "https://www.mk.co.kr/news/business/12028082",
    "pub_date": "Mon, 27 Apr 2026 11:06:17 +09:00",
    "fetched_at": "2026-04-27T03:52:57.759898Z"
  },
  {
    "title": "“나는 얼마 받지?”…‘고유가 지원금’ 오늘부터 지급",
    "link": "https://www.mk.co.kr/news/business/12028037",
    "pub_date": "Mon, 27 Apr 2026 10:41:52 +09:00",
    "fetched_at": "2026-04-27T03:52:57.759902Z"
  }
]